MANIFEST.in
setup.py
reactopya_examples/__init__.py
reactopya_examples/_version.py
reactopya_examples/all_widgets.py
reactopya_examples/init.py
reactopya_examples/reactopyacolabwidget.py
reactopya_examples/reactopyaelectronwidget.py
reactopya_examples/shellscript.py
reactopya_examples.egg-info/PKG-INFO
reactopya_examples.egg-info/SOURCES.txt
reactopya_examples.egg-info/dependency_links.txt
reactopya_examples.egg-info/requires.txt
reactopya_examples.egg-info/top_level.txt
reactopya_examples/dist/bundle.js
reactopya_examples/electron/src/index.js
reactopya_examples/electron/src/preload.js
reactopya_examples/electron/web/index.html
reactopya_examples/widgets/__init__.py
reactopya_examples/widgets/create_sync.py
reactopya_examples/widgets/jupyter.py
reactopya_examples/widgets/Accordion/Accordion.py
reactopya_examples/widgets/Accordion/__init__.py
reactopya_examples/widgets/HBox/HBox.py
reactopya_examples/widgets/HBox/__init__.py
reactopya_examples/widgets/InteractivePlotly/InteractivePlotly.py
reactopya_examples/widgets/InteractivePlotly/__init__.py
reactopya_examples/widgets/PlotlyExample/PlotlyExample.py
reactopya_examples/widgets/PlotlyExample/__init__.py
reactopya_examples/widgets/Tabs/Tabs.py
reactopya_examples/widgets/Tabs/__init__.py
reactopya_examples/widgets/VBox/VBox.py
reactopya_examples/widgets/VBox/__init__.py
reactopya_examples/widgets/VtkCone/VtkCone.py
reactopya_examples/widgets/VtkCone/__init__.py