Metadata-Version: 1.1
Name: reactopya-examples
Version: 0.6.0
Summary: Gallery of example reactopya widgets
Home-page: UNKNOWN
Author: Jeremy Magland
Author-email: UNKNOWN
License: UNKNOWN
Platform: UNKNOWN
Classifier: Programming Language :: Python :: 3
Classifier: License :: OSI Approved :: Apache Software License
Classifier: Operating System :: OS Independent
